factoai/__init__.py
factoai-0.0.0.dist-info/METADATA
factoai-0.0.0.dist-info/WHEEL
factoai-0.0.0.dist-info/RECORD
