Metadata-Version: 2.1
Name: factoai
Version: 0.0.0
Summary: The AI toolkit with applications in minds
Author: altar31
Author-email: damien.sicard31@gmail.com
Requires-Python: >=3.11,<4.0
Classifier: Programming Language :: Python :: 3
Classifier: Programming Language :: Python :: 3.11
